.gitignore
AUTHORS.txt
CHANGES.txt
INSTALL
LICENSE.txt
README.txt
VERSION.txt
setup.py
doc/templates.txt
lib/Booktype.egg-info/PKG-INFO
lib/Booktype.egg-info/SOURCES.txt
lib/Booktype.egg-info/dependency_links.txt
lib/Booktype.egg-info/requires.txt
lib/Booktype.egg-info/top_level.txt
lib/booki/__init__.py
lib/booki/bookizip.py
lib/booki/manage.py
lib/booki/settings.py.original
lib/booki/urls.py
lib/booki/account/__init__.py
lib/booki/account/models.py
lib/booki/account/signals.py
lib/booki/account/tests.py
lib/booki/account/urls.py
lib/booki/account/views.py
lib/booki/account/migrations/0001_initial.py
lib/booki/account/migrations/__init__.py
lib/booki/account/templates/account/create_book.html
lib/booki/account/templates/account/create_book_redirect.html
lib/booki/account/templates/account/create_group.html
lib/booki/account/templates/account/error_import.html
lib/booki/account/templates/account/forgot_password.html
lib/booki/account/templates/account/forgot_password_enter.html
lib/booki/account/templates/account/form_register.html
lib/booki/account/templates/account/form_signin.html
lib/booki/account/templates/account/import_book.html
lib/booki/account/templates/account/my_books.html
lib/booki/account/templates/account/my_groups.html
lib/booki/account/templates/account/my_people.html
lib/booki/account/templates/account/password_reset_email.txt
lib/booki/account/templates/account/signin.html
lib/booki/account/templates/account/view_profile.html
lib/booki/account/templates/errors/user_does_not_exist.html
lib/booki/account/templatetags/__init__.py
lib/booki/account/templatetags/profile.py
lib/booki/channels/__init__.py
lib/booki/channels/chat.py
lib/booki/channels/editor.py
lib/booki/channels/group.py
lib/booki/channels/main.py
lib/booki/channels/profile.py
lib/booki/editor/__init__.py
lib/booki/editor/admin.py
lib/booki/editor/common.py
lib/booki/editor/models.py
lib/booki/editor/signals.py
lib/booki/editor/tests.py
lib/booki/editor/urls.py
lib/booki/editor/views.py
lib/booki/editor/fixtures/documentation_licenses.json
lib/booki/editor/management/__init__.py
lib/booki/editor/management/commands/__init__.py
