Metadata-Version: 1.0
Name: Booktype
Version: 1.5
Summary: FLOSS Manuals collaborative book writing tool
Home-page: http://booki-dev.flossmanuals.net/
Author: Aleksandar Erkalovic
Author-email: aerkalov@gmail.com
License: GPL
Keywords: collaborative book writing sprint
Platform: UNKNOWN
Classifier: License :: OSI Approved :: GNU General Public License (GPL)
Classifier: Programming Language :: Python
Classifier: Development Status :: 3 - Alpha
Classifier: Intended Audience :: Developers
Classifier: Intended Audience :: Information Technology
Classifier: Framework :: Django
